hasss.py
hasss-0.2.6.dist-info/METADATA
hasss-0.2.6.dist-info/WHEEL
hasss-0.2.6.dist-info/entry_points.txt
hasss-0.2.6.dist-info/top_level.txt
hasss-0.2.6.dist-info/RECORD
