Metadata-Version: 2.4
Name: hasss
Version: 0.2.6
Summary: A command line tool to determine if a proxy list has shadowsocks proxies.
Author-email: "Jorge Alberto Díaz Orozco (Akiel)" <diazorozcoj@gmail.com>
License-Expression: GPL-3.0-or-later
Requires-Dist: requests
Requires-Dist: click
